pyapep/__init__.py
pyapep/simsep.py
pyapep/simsto.py
sebyga-0.0.4.dist-info/METADATA
sebyga-0.0.4.dist-info/WHEEL
sebyga-0.0.4.dist-info/top_level.txt
sebyga-0.0.4.dist-info/RECORD
